ihr/__init__.py
ihr/delay.py
ihr/disconnect.py
ihr/forwarding.py
ihr/hegemony.py
abondance-0.1.0.dist-info/LICENSE
abondance-0.1.0.dist-info/METADATA
abondance-0.1.0.dist-info/WHEEL
abondance-0.1.0.dist-info/top_level.txt
abondance-0.1.0.dist-info/RECORD
