Metadata-Version: 2.1
Name: abondance
Version: 0.1.0
Summary: Pyhton library for Internet Health Report API
Home-page: https://github.com/InternetHealthReport/abondance
Author: Romain Fontugne
License: UNKNOWN
Platform: UNKNOWN
Requires-Dist: arrow
Requires-Dist: requests-futures
